<annotation>
	<folder>data</folder>
	<filename>GOMCAM 20191001_1353200297.png</filename>
	<path>C:\labeling\labeling_tool\data\GOMCAM 20191001_1353200297.png</path>
	<source>
		<database>Unknown</database>
	</source>
	<size>
		<width>640</width>
		<height>480</height>
		<depth>3</depth>
	</size>
	<segmented>0</segmented>
	<object>
		<name>Ojjam</name>
		<pose>Unspecified</pose>
		<truncated>1</truncated>
		<difficult>0</difficult>
		<bndbox>
			<xmin>97</xmin>
			<ymin>1</ymin>
			<xmax>320</xmax>
			<ymax>166</ymax>
		</bndbox>
	</object>
	<object>
		<name>Chicchok_Tiramisu</name>
		<pose>Unspecified</pose>
		<truncated>0</truncated>
		<difficult>0</difficult>
		<bndbox>
			<xmin>219</xmin>
			<ymin>179</ymin>
			<xmax>635</xmax>
			<ymax>269</ymax>
		</bndbox>
	</object>
	<object>
		<name>Pocachip_Onion</name>
		<pose>Unspecified</pose>
		<truncated>1</truncated>
		<difficult>0</difficult>
		<bndbox>
			<xmin>54</xmin>
			<ymin>288</ymin>
			<xmax>429</xmax>
			<ymax>480</ymax>
		</bndbox>
	</object>
	<object>
		<name>Udongmini</name>
		<pose>Unspecified</pose>
		<truncated>1</truncated>
		<difficult>0</difficult>
		<bndbox>
			<xmin>455</xmin>
			<ymin>288</ymin>
			<xmax>628</xmax>
			<ymax>480</ymax>
		</bndbox>
	</object>
	<object>
		<name>Hush_Choco_Drink</name>
		<pose>Unspecified</pose>
		<truncated>0</truncated>
		<difficult>0</difficult>
		<bndbox>
			<xmin>5</xmin>
			<ymin>114</ymin>
			<xmax>184</xmax>
			<ymax>253</ymax>
		</bndbox>
	</object>
</annotation>
