<annotation>
	<folder>data</folder>
	<filename>GOMCAM 20191001_1352010245.png</filename>
	<path>C:\labeling\labeling_tool\data\GOMCAM 20191001_1352010245.png</path>
	<source>
		<database>Unknown</database>
	</source>
	<size>
		<width>640</width>
		<height>480</height>
		<depth>3</depth>
	</size>
	<segmented>0</segmented>
	<object>
		<name>Pocachip_Onion</name>
		<pose>Unspecified</pose>
		<truncated>1</truncated>
		<difficult>0</difficult>
		<bndbox>
			<xmin>23</xmin>
			<ymin>216</ymin>
			<xmax>480</xmax>
			<ymax>480</ymax>
		</bndbox>
	</object>
	<object>
		<name>Ojjam</name>
		<pose>Unspecified</pose>
		<truncated>0</truncated>
		<difficult>0</difficult>
		<bndbox>
			<xmin>179</xmin>
			<ymin>57</ymin>
			<xmax>402</xmax>
			<ymax>260</ymax>
		</bndbox>
	</object>
	<object>
		<name>Udongmini</name>
		<pose>Unspecified</pose>
		<truncated>0</truncated>
		<difficult>0</difficult>
		<bndbox>
			<xmin>379</xmin>
			<ymin>62</ymin>
			<xmax>585</xmax>
			<ymax>243</ymax>
		</bndbox>
	</object>
	<object>
		<name>Hush_Choco_Drink</name>
		<pose>Unspecified</pose>
		<truncated>1</truncated>
		<difficult>0</difficult>
		<bndbox>
			<xmin>452</xmin>
			<ymin>199</ymin>
			<xmax>640</xmax>
			<ymax>433</ymax>
		</bndbox>
	</object>
	<object>
		<name>Chicchok_Tiramisu</name>
		<pose>Unspecified</pose>
		<truncated>1</truncated>
		<difficult>0</difficult>
		<bndbox>
			<xmin>21</xmin>
			<ymin>1</ymin>
			<xmax>174</xmax>
			<ymax>321</ymax>
		</bndbox>
	</object>
</annotation>
