<annotation>
	<folder>woohyuk_data_for_detection</folder>
	<filename>GOMCAM 20191001_1043430754.png</filename>
	<path>C:\Users\jangw\Documents\lotte\LABELIMG\woohyuk_data_for_detection\GOMCAM 20191001_1043430754.png</path>
	<source>
		<database>Unknown</database>
	</source>
	<size>
		<width>640</width>
		<height>480</height>
		<depth>3</depth>
	</size>
	<segmented>0</segmented>
	<object>
		<name>Chilseong_Cider_1.5L</name>
		<pose>Unspecified</pose>
		<truncated>1</truncated>
		<difficult>0</difficult>
		<bndbox>
			<xmin>455</xmin>
			<ymin>2</ymin>
			<xmax>640</xmax>
			<ymax>475</ymax>
		</bndbox>
	</object>
	<object>
		<name>Post-meal_recipe_W_tea_500ml</name>
		<pose>Unspecified</pose>
		<truncated>0</truncated>
		<difficult>0</difficult>
		<bndbox>
			<xmin>47</xmin>
			<ymin>28</ymin>
			<xmax>407</xmax>
			<ymax>154</ymax>
		</bndbox>
	</object>
	<object>
		<name>Hush_Choco_Drink</name>
		<pose>Unspecified</pose>
		<truncated>0</truncated>
		<difficult>0</difficult>
		<bndbox>
			<xmin>95</xmin>
			<ymin>130</ymin>
			<xmax>305</xmax>
			<ymax>254</ymax>
		</bndbox>
	</object>
	<object>
		<name>Oninon_Ring</name>
		<pose>Unspecified</pose>
		<truncated>1</truncated>
		<difficult>0</difficult>
		<bndbox>
			<xmin>3</xmin>
			<ymin>232</ymin>
			<xmax>520</xmax>
			<ymax>480</ymax>
		</bndbox>
	</object>
</annotation>
