<annotation>
	<folder>detection_data</folder>
	<filename>GOMCAM 20191001_1500030056.png</filename>
	<path>C:\Users\ncbaicam\Documents\[kiro]project\detection_data\GOMCAM 20191001_1500030056.png</path>
	<source>
		<database>Unknown</database>
	</source>
	<size>
		<width>640</width>
		<height>480</height>
		<depth>3</depth>
	</size>
	<segmented>0</segmented>
	<object>
		<name>Seagram_Lemon_Carbonated_Water</name>
		<pose>Unspecified</pose>
		<truncated>0</truncated>
		<difficult>0</difficult>
		<bndbox>
			<xmin>286</xmin>
			<ymin>74</ymin>
			<xmax>633</xmax>
			<ymax>253</ymax>
		</bndbox>
	</object>
	<object>
		<name>GooGoo_Cone_CVS</name>
		<pose>Unspecified</pose>
		<truncated>0</truncated>
		<difficult>0</difficult>
		<bndbox>
			<xmin>280</xmin>
			<ymin>214</ymin>
			<xmax>593</xmax>
			<ymax>355</ymax>
		</bndbox>
	</object>
	<object>
		<name>Pocachip_Onion</name>
		<pose>Unspecified</pose>
		<truncated>1</truncated>
		<difficult>0</difficult>
		<bndbox>
			<xmin>123</xmin>
			<ymin>185</ymin>
			<xmax>590</xmax>
			<ymax>480</ymax>
		</bndbox>
	</object>
	<object>
		<name>Hejangmini</name>
		<pose>Unspecified</pose>
		<truncated>0</truncated>
		<difficult>0</difficult>
		<bndbox>
			<xmin>6</xmin>
			<ymin>237</ymin>
			<xmax>186</xmax>
			<ymax>417</ymax>
		</bndbox>
	</object>
	<object>
		<name>Jinlamyeon_Hot_Taste_Large_Cup</name>
		<pose>Unspecified</pose>
		<truncated>1</truncated>
		<difficult>0</difficult>
		<bndbox>
			<xmin>24</xmin>
			<ymin>1</ymin>
			<xmax>297</xmax>
			<ymax>263</ymax>
		</bndbox>
	</object>
</annotation>
